asa_api_client/__init__.py
asa_api_client/auth.py
asa_api_client/client.py
asa_api_client/exceptions.py
asa_api_client/logging.py
asa_api_client/settings.py
asa_api_client/models/__init__.py
asa_api_client/models/ad_groups.py
asa_api_client/models/base.py
asa_api_client/models/campaigns.py
asa_api_client/models/keywords.py
asa_api_client/models/reports.py
asa_api_client/resources/__init__.py
asa_api_client/resources/ad_groups.py
asa_api_client/resources/base.py
asa_api_client/resources/campaigns.py
asa_api_client/resources/custom_reports.py
asa_api_client/resources/keywords.py
asa_api_client/resources/reports.py
asa_api_client/utils/__init__.py
asa_api_client-0.1.6.dist-info/METADATA
asa_api_client-0.1.6.dist-info/WHEEL
asa_api_client-0.1.6.dist-info/licenses/LICENSE
asa_api_client-0.1.6.dist-info/RECORD
