Metadata-Version: 2.4
Name: asa-api-client
Version: 0.1.6
Summary: A modern Python client for the Apple Search Ads API with full type safety and async support
Project-URL: Homepage, https://github.com/SamPetherbridge/asa-api-client
Project-URL: Documentation, https://asa-api-client.peth.au
Project-URL: Repository, https://github.com/SamPetherbridge/asa-api-client
Project-URL: Issues, https://github.com/SamPetherbridge/asa-api-client/issues
Author-email: Sam Petherbridge <hello@peth.me>
License-Expression: MIT
License-File: LICENSE
Keywords: advertising,api,apple,asa,async,pydantic,search-ads
Classifier: Development Status :: 4 - Beta
Classifier: Framework :: Pydantic :: 2
Classifier: Intended Audience :: Developers
Classifier: License :: OSI Approved :: MIT License
Classifier: Operating System :: OS Independent
Classifier: Programming Language :: Python :: 3
Classifier: Programming Language :: Python :: 3.13
Classifier: Typing :: Typed
Requires-Python: >=3.13
Requires-Dist: httpx>=0.27.0
Requires-Dist: pydantic-settings>=2.6.0
Requires-Dist: pydantic>=2.10.0
Requires-Dist: pyjwt[crypto]>=2.9.0
Provides-Extra: dev
Requires-Dist: mypy>=1.13.0; extra == 'dev'
Requires-Dist: pandas-stubs>=2.2.0; extra == 'dev'
Requires-Dist: pandas>=2.2.0; extra == 'dev'
Requires-Dist: pre-commit>=4.0.0; extra == 'dev'
Requires-Dist: pytest-asyncio>=0.24.0; extra == 'dev'
Requires-Dist: pytest-cov>=6.0.0; extra == 'dev'
Requires-Dist: pytest-httpx>=0.34.0; extra == 'dev'
Requires-Dist: pytest>=8.3.0; extra == 'dev'
Requires-Dist: ruff>=0.8.0; extra == 'dev'
Provides-Extra: docs
Requires-Dist: mkdocs-material>=9.5.0; extra == 'docs'
Requires-Dist: mkdocs>=1.6.0; extra == 'docs'
Requires-Dist: mkdocstrings[python]>=0.27.0; extra == 'docs'
Provides-Extra: pandas
Requires-Dist: pandas>=2.2.0; extra == 'pandas'
